{
  "fullName": "John Doe",
  "email": "johndoe@gmail.com",
  "resume": "https://www.w3.org/WAI/ER/tests/xhtml/testfiles/resources/pdf/dummy.pdf",
  "profilePicture": "https://images.pexels.com/photos/771742/pexels-photo-771742.jpeg",
  "homepage": {
    "bio": "I'm a software engineer specializing in building (and occasionally designing) exceptional digital experiences. Currently, I'm focused on building accessible, human-centered products at XYZ company. Prior to XYZ, I worked at ABC, where I learned the ins and outs of the industry. During that time, I also got to implement a lot of neat projects.",
    "skills": {
      "description": "I have worked with a variety of technologies and tools in my 2+ yr of professional journey. Here are some of them."
    },
    "gallery": {
      "description": "I love to capture moments so here are some of my best shots from my phone camera.",
      "photos": [
        "https://images.unsplash.com/photo-1557683316-973673baf926",
        "https://images.unsplash.com/photo-1557683316-973673baf926",
        "https://images.unsplash.com/photo-1557683316-973673baf926",
        "https://images.unsplash.com/photo-1557683316-973673baf926",
        "https://images.unsplash.com/photo-1557683316-973673baf926",
        "https://images.unsplash.com/photo-1557683316-973673baf926",
        "https://images.unsplash.com/photo-1557683316-973673baf926",
        "https://images.unsplash.com/photo-1557683316-973673baf926",
        "https://images.unsplash.com/photo-1557683316-973673baf926",
        "https://images.unsplash.com/photo-1557683316-973673baf926",
        "https://images.unsplash.com/photo-1557683316-973673baf926",
        "https://images.unsplash.com/photo-1557683316-973673baf926"
      ]
    }
  }
}